
main <t7.lua:0,0> (6 instructions at 0x7fb0ea4048c0)
0+ params, 2 slots, 1 upvalue, 0 locals, 2 constants, 1 function
	1	[4]	CLOSURE  	0 0	; 0x7fb0ea404b00
	2	[1]	SETTABUP 	0 -1 0	; _ENV "hello"
	3	[6]	GETTABUP 	0 0 -1	; _ENV "hello"
	4	[6]	CALL     	0 1 2
	5	[6]	SETTABUP 	0 -2 0	; _ENV "b"
	6	[6]	RETURN   	0 1
constants (2) for 0x7fb0ea4048c0:
	1	"hello"
	2	"b"
locals (0) for 0x7fb0ea4048c0:
upvalues (1) for 0x7fb0ea4048c0:
	0	_ENV	1	0

function <t7.lua:1,4> (5 instructions at 0x7fb0ea404b00)
0 params, 2 slots, 0 upvalues, 1 local, 2 constants, 0 functions
	1	[2]	LOADK    	0 -1	; 10
	2	[3]	UNM      	1 0
	3	[3]	MOD      	1 1 -2
	4	[3]	RETURN   	1 2
	5	[4]	RETURN   	0 1
constants (2) for 0x7fb0ea404b00:
	1	10
	2	3
locals (1) for 0x7fb0ea404b00:
	0	a	2	6
upvalues (0) for 0x7fb0ea404b00:
